[{"neighbors":[],"data":{"name":"Castle Black","castle":0,"supply":0,"crown":1,"landscape":"ground"},"id":0},{"neighbors":[],"data":{"name":"Bay of Ice","castle":0,"supply":0,"crown":0,"landscape":"water"},"id":1},{"neighbors":[],"data":{"name":"Karhold","castle":1,"supply":0,"crown":0,"landscape":"ground"},"id":2},{"neighbors":[],"data":{"name":"The Shivering Sea","castle":0,"supply":0,"crown":0,"landscape":"water"},"id":3},{"neighbors":[],"data":{"name":"Winterfell","castle":2,"supply":1,"crown":1,"landscape":"ground"},"id":4}]